<?xml version="1.0" encoding="utf-8" ?>
<dwsync>
<file name="input_text_right.gif" server="ftp.thevintagetable.net/karatenew/" local="128940324680000000" remote="130278153000000000" Dst="2" />
<file name="input_text_left.gif" server="ftp.thevintagetable.net/karatenew/" local="128940304990000000" remote="130278153000000000" Dst="2" />
<file name="input_right-focus.gif" server="ftp.thevintagetable.net/karatenew/" local="128669097620000000" remote="130278153000000000" Dst="2" />
<file name="input_right-hover.gif" server="ftp.thevintagetable.net/karatenew/" local="128669097410000000" remote="130278153000000000" Dst="2" />
<file name="input_right.gif" server="ftp.thevintagetable.net/karatenew/" local="128669096640000000" remote="130278153000000000" Dst="2" />
<file name="input_left.gif" server="ftp.thevintagetable.net/karatenew/" local="128668940560000000" remote="130278153000000000" Dst="2" />
<file name="input_left-focus.gif" server="ftp.thevintagetable.net/karatenew/" local="128668892430000000" remote="130278153000000000" Dst="2" />
<file name="input_left-hover.gif" server="ftp.thevintagetable.net/karatenew/" local="128668892110000000" remote="130278153000000000" Dst="2" />
</dwsync>